{
  "id": 19,
  "title": "Romania & Bulgaria: Emerging Black Sea Markets",
  "slug": "romania-bulgaria-charcoal-market-black-sea",
  "excerpt": "Analyzing the growing charcoal import opportunities in Romania and Bulgaria along the Black Sea coast.",
  "content": "Romania and Bulgaria represent promising emerging markets for coconut charcoal along the Black Sea coast. With combined populations exceeding 30 million, these markets offer substantial scale alongside growing consumer sophistication.\n\nRomania, with a population of approximately 19 million, demonstrates the larger market potential. Bucharest serves as the primary demand center, but coastal resorts along the Black Sea (Mamaia, Constanța) and the Transylvanian region show growing interest in premium charcoal products.\n\nBulgaria's market, while smaller (approximately 6.9 million population), benefits significantly from its established tourism industry. Sunny Beach, Golden Sands, and other coastal resorts consume substantial charcoal volumes during the summer season, serving both tourists and local hospitality establishments.\n\nBoth countries follow EU import regulations, facilitating straightforward customs procedures for Indonesian charcoal products. The Port of Constanța in Romania serves as a key entry point, while Burgas handles much of Bulgaria's maritime imports.\n\nThe retail landscape in both countries is dominated by hypermarket chains (Carrefour, Auchan, Metro) and local retail groups. HORECA (Hotel/Restaurant/Café) distribution channels are well-developed in tourist areas.\n\nPrice sensitivity remains higher than Western European markets, but quality awareness is growing. Indonesian coconut charcoal can compete effectively on value proposition, particularly for barbecue and shisha applications.",
  "category": "Market Insights",
  "tags": ["Romania", "Bulgaria", "Black Sea", "Tourism", "Import", "Emerging Markets"],
  "status": "draft",
  "publish_date": null
}